drf_haystack_search_filter/__init__.py
drf_haystack_search_filter/filters.py
drf_haystack_search_filter-1.3.0.dist-info/METADATA
drf_haystack_search_filter-1.3.0.dist-info/WHEEL
drf_haystack_search_filter-1.3.0.dist-info/licenses/LICENSE
drf_haystack_search_filter-1.3.0.dist-info/RECORD
