Metadata-Version: 2.4
Name: drf-haystack-search-filter
Version: 1.3.0
Summary: A django-haystack search filter for Django Rest Framework.
Project-URL: Homepage, https://github.com/stefanofusai/drf-haystack-search-filter
Project-URL: Repository, https://github.com/stefanofusai/drf-haystack-search-filter
Author-email: Stefano Fusai <stefanofusai@gmail.com>
Maintainer-email: Stefano Fusai <stefanofusai@gmail.com>
License-File: LICENSE
Requires-Python: >=3.12
Requires-Dist: django-haystack<4.0.0,>=3.0
Requires-Dist: django<6.0.0,>=5.0.0
Requires-Dist: djangorestframework<4.0.0,>=3.0.0
